shisis/__init__.py
shisis/__main__.py
shisis/py.typed
shisis_async-1.2.2.dist-info/licenses/LICENSE
shisis_async-1.2.2.dist-info/METADATA
shisis_async-1.2.2.dist-info/WHEEL
shisis_async-1.2.2.dist-info/entry_points.txt
shisis_async-1.2.2.dist-info/top_level.txt
shisis_async-1.2.2.dist-info/RECORD
