Metadata-Version: 2.4
Name: shisis-async
Version: 1.2.2
Summary: TU-Berlin Isis Shibboleth login library
Author-email: bchmnn <shisis@gandalf.mozmail.com>
License:                     GNU GENERAL PUBLIC LICENSE
Project-URL: Repository, https://github.com/bchmnn/shisis-async
Keywords: Moodle,Isis,Shibboleth,TU-Berlin,Authentication
Requires-Python: >=3.9
License-File: LICENSE
Requires-Dist: aiohttp<4.0,>=3.0
Requires-Dist: beautifulsoup4<5.0,>=4.0
Requires-Dist: lxml<7.0,>=5.0
Provides-Extra: dev
Requires-Dist: pip-tools; extra == "dev"
Requires-Dist: black; extra == "dev"
Requires-Dist: mypy; extra == "dev"
Requires-Dist: pyright; extra == "dev"
Requires-Dist: ruff; extra == "dev"
Requires-Dist: pylint; extra == "dev"
Requires-Dist: isort; extra == "dev"
Dynamic: license-file
